sweeping_view/__init__.py
sweeping_view/_version.py
sweeping_view/avf.py
sweeping_view/base.py
sweeping_view/evf.py
sweeping_view/exceptions.py
sweeping_view/mime_types.py
sweeping_view/rmv.py
sweeping_view-0.3.2.dist-info/LICENSE.txt
sweeping_view-0.3.2.dist-info/METADATA
sweeping_view-0.3.2.dist-info/WHEEL
sweeping_view-0.3.2.dist-info/top_level.txt
sweeping_view-0.3.2.dist-info/RECORD
